{
  "org_id": "KR-MEDIA-003",
  "basic_info": {
    "name_original": "주식회사 에스비에스",
    "name_zh": "SBS（首尔广播公司）",
    "name_en": "Seoul Broadcasting System",
    "aliases": [
      "SBS",
      "서울방송",
      "Seoul Bangsong",
      "株式会社SBS"
    ],
    "org_type": "MEDIA",
    "org_subtype": "broadcaster",
    "country_iso3": "KOR",
    "hq_country_iso3": "KOR",
    "founded_date": "1990-11-14",
    "website": "https://www.sbs.co.kr"
  },
  "social_accounts": [
    {
      "platform": "youtube",
      "account_name": "@SBSNOW",
      "url": "https://www.youtube.com/@SBSNOW1",
      "source": "official website"
    },
    {
      "platform": "youtube",
      "account_name": "SBS 뉴스",
      "url": "https://www.youtube.com/channel/UCkinYTS9IHqOEwR1Sze2JTw",
      "source": "official website"
    },
    {
      "platform": "youtube",
      "account_name": "SBS 스브스 Drama",
      "url": "https://www.youtube.com/channel/UC6erIDuvbOaAO-OT5rB2Xew",
      "source": "official website"
    },
    {
      "platform": "instagram",
      "account_name": "@sbsnow_insta",
      "url": "https://www.instagram.com/sbsnow_insta/",
      "source": "official website"
    },
    {
      "platform": "facebook",
      "account_name": "SBS",
      "url": "https://www.facebook.com/sbs",
      "source": "official website"
    },
    {
      "platform": "twitter_x",
      "account_name": "@SBSNOW",
      "url": "https://x.com/SBSNOW",
      "source": "official website"
    }
  ],
  "digital_assets": [
    {
      "name": "SBS 공식 홈페이지",
      "url": "https://www.sbs.co.kr",
      "description": "SBS官方网站，提供直播、节目回放和新闻",
      "source": "official"
    },
    {
      "name": "SBS 뉴스",
      "url": "https://news.sbs.co.kr",
      "description": "SBS新闻网站",
      "source": "official"
    },
    {
      "name": "SBS Global",
      "url": "http://global.sbs.co.kr",
      "description": "SBS国际版本网站",
      "source": "official"
    },
    {
      "name": "SBS play (VOD)",
      "url": "https://allvod.sbs.co.kr",
      "description": "SBS视频点播平台",
      "source": "official"
    },
    {
      "name": "SBS 스타",
      "url": "https://star.sbs.co.kr",
      "description": "SBS明星粉丝服务平台",
      "source": "official"
    }
  ],
  "key_people": [
    {
      "person_id": null,
      "name": "Bang Moon-shin (방문신)",
      "title": "社长兼CEO",
      "title_description": "SBS代表理事社长，同时兼任韩国广播协会第27代会长",
      "description": "1963年11月30日生，首尔大学经营学科学士。1989年加入韩国日报成为记者，1991年作为SBS创社成员加入，历任东京特派员、政治部长、国际部长、编辑部长、报道及对外合作总管副社长。2023年12月1日就任SBS第11任社长。2024年8月就任韩国广播协会会长。"
    }
  ],
  "departments": [
    {
      "dept_id": "KR-MEDIA-003-DEPT-001",
      "name": "报道局",
      "head": null,
      "description": "负责SBS新闻报道的采编与播出，包括SBS 8点新闻、早间新闻等旗舰新闻节目",
      "parent_dept_id": null
    },
    {
      "dept_id": "KR-MEDIA-003-DEPT-002",
      "name": "电视剧中心（Studio S）",
      "head": null,
      "description": "负责SBS电视剧的策划与制作，2020年从内部部门分拆为独立子公司Studio S运营",
      "parent_dept_id": null
    },
    {
      "dept_id": "KR-MEDIA-003-DEPT-003",
      "name": "综艺中心",
      "head": null,
      "description": "负责SBS综艺节目的策划与制作，涵盖Running Man、我家的熊孩子等人气节目",
      "parent_dept_id": null
    }
  ],
  "recent_events": [
    {
      "date": "2026-04-22",
      "title": "SBS就2026年北美世界杯转播权谈判破裂发表声明",
      "description": "SBS发表官方立场称，与2026年FIFA北美世界杯转播权相关的谈判破裂，JTBC等竞争对手获得转播权，SBS将首次缺席世界杯转播。",
      "impact": "SBS自成立以来首次未能获得世界杯转播权，标志着韩国体育转播格局的重大变化",
      "source": "https://www.mk.co.kr/en/hot-issues/12024191"
    },
    {
      "date": "2026-04-21",
      "title": "SBS与新加坡IMDA签署内容联合制作协议",
      "description": "SBS与新加坡资讯通信媒体发展局（IMDA）正式签署合作伙伴关系，共同制作面向全球观众的电视剧和综艺节目。SBS社长方文信与IMDA媒体产业集团副代表出席签约仪式。",
      "impact": "拓展SBS国际内容市场，深化与东南亚的媒体合作",
      "source": "https://www.asiaone.com/singapore/dramas-variety-shows-imda-and-south-koreas-sbs-formalise-partnership-co-produce-content"
    },
    {
      "date": "2026-02-10",
      "title": "SBS公布2026年电视剧阵容",
      "description": "SBS公布2026年电视剧计划，延续2025年8.2%平均收视率的成功态势，推出包括《美好的新世界》《金部长》《FlexxCop 2》《Good Partner 2》等新剧及续作。",
      "impact": "继续巩固SBS在韩剧市场的领先地位",
      "source": "https://www.chosun.com/english/kpop-culture-en/2026/02/10/4JK4I55BUJG2BNYJFZKYZ35J4I/"
    },
    {
      "date": "2024-12-20",
      "title": "SBS与Netflix签署六年内容供应协议",
      "description": "SBS与Netflix签署具有里程碑意义的六年内容供应协议，自2025年1月1日起向Netflix提供新播电视剧、综艺节目、教育节目及经典库内容。消息公布后SBS股价单日涨停（涨30%）。",
      "impact": "韩国地面波电视台与全球流媒体平台的标志性合作，深刻改变韩国媒体行业格局",
      "source": "https://pulse.mk.co.kr/news/english/11201202"
    },
    {
      "date": "2026-01-01",
      "title": "SBS成为韩国首个对AI训练使用新闻数据收费的电视台",
      "description": "SBS建立了正式的新闻数据AI训练许可收费框架，成为韩国首家对AI训练使用其新闻数据收取费用的全国性电视台。",
      "impact": "在AI时代为新闻媒体内容价值确立先例",
      "source": "https://www.koreaherald.com/article/10572608"
    }
  ],
  "related_entities": [
    {
      "org_id": "KR-MEDIA-001",
      "org_name": "韩国广播公司 (Korean Broadcasting System)",
      "org_type": "MEDIA",
      "org_description": "韩国公共广播公司（KBS），三大地面波电视台之一",
      "relationship_type": "sibling"
    },
    {
      "org_id": "KR-MEDIA-002",
      "org_name": "韩国文化广播公司 (Munhwa Broadcasting Corporation)",
      "org_type": "MEDIA",
      "org_description": "韩国文化广播公司（MBC），三大地面波电视台之一",
      "relationship_type": "sibling"
    },
    {
      "org_id": "KR-MEDIA-012",
      "org_name": "JTBC (JTBC)",
      "org_type": "MEDIA",
      "org_description": "韩国综合编成频道，中央日报旗下电视台",
      "relationship_type": "sibling"
    },
    {
      "org_id": "KR-MEDIA-004",
      "org_name": "韩联社 (Yonhap News Agency)",
      "org_type": "MEDIA",
      "org_description": "韩国联合通讯社",
      "relationship_type": "partner"
    },
    {
      "org_id": "KR-CORP-020",
      "org_name": "TY Holdings (티와이홀딩스)",
      "org_type": "CORP",
      "org_description": "泰荣建设旗下控股公司，持有SBS约36.92%股份，为最大股东",
      "relationship_type": "controlling_shareholder"
    },
    {
      "org_id": "KR-CORP-020",
      "org_name": "首尔广播公司 Media Holdings (SBS Media Holdings)",
      "org_type": "MEDIA",
      "org_description": "SBS媒体控股公司，SBS的母公司（KRX: 101060）",
      "relationship_type": "parent_org"
    },
    {
      "org_id": "KR-MEDIA-019",
      "org_name": "Studio S",
      "org_type": "MEDIA",
      "org_description": "SBS旗下电视剧制作子公司，2020年从SBS电视剧制作部门独立",
      "relationship_type": "subsidiary"
    },
    {
      "org_id": "KR-MEDIA-020",
      "org_name": "首尔广播公司 Contents Hub (SBS Contents Hub)",
      "org_type": "MEDIA",
      "org_description": "SBS旗下在线媒体内容发行子公司",
      "relationship_type": "subsidiary"
    },
    {
      "org_id": "KR-MEDIA-021",
      "org_name": "首尔广播公司 Medianet (SBS Medianet)",
      "org_type": "MEDIA",
      "org_description": "SBS旗下有线电视频道运营公司，运营SBS F!L、SBS Biz、SBS Sports、SBS Golf等频道",
      "relationship_type": "subsidiary"
    }
  ],
  "core_business": "SBS（首尔广播公司）是韩国最大的民营地面波广播电视公司，成立于1990年11月14日，1991年12月9日正式开播。公司运营1个全国性地面波电视频道（SBS TV，6频道）和3个广播电台（Power FM、Love FM、V-Radio），通过10家地方联播网成员覆盖韩国全国。此外还运营8个有线电视频道（SBS Plus、SBS Golf、SBS Golf 2、SBS funE、SBS Life、SBS Sports、SBS Biz、SBS F!L UHD）。SBS以电视剧和综艺节目闻名，代表作品包括《沙漏》《来自星星的你》《Running Man》等，是韩流文化传播的重要推手。2024年12月与Netflix签署六年内容供应协议，2026年4月与新加坡IMDA签署联合制作协议，持续推进全球化战略。公司股票在韩国交易所上市（KRX: 034120），母公司为SBS Media Holdings，最大股东为TY Holdings（泰荣建设旗下控股公司）。",
  "industries": [
    "broadcasting",
    "digital_media",
    "media_publishing",
    "gaming"
  ],
  "apec_stance": "作为韩国主要广播电视媒体，SBS积极参与亚太地区媒体合作。SBS与新加坡IMDA于2026年4月签署内容联合制作协议，与东南亚多个媒体平台保持合作关系。通过Netflix内容供应协议向全球输出韩流内容，服务APEC多个经济体（日本、中国、东南亚等）。SBS与日本电视台（NTV）、中国央视（CCTV）、新加坡新传媒（MediaCorp）等APEC经济体主流媒体建有姊妹台关系。",
  "profile": {
    "source_url": "https://upload.wikimedia.org/wikipedia/commons/thumb/c/c0/Seoul_Broadcasting_System_logo.svg/250px-Seoul_Broadcasting_System_logo.svg.png",
    "local_path": null
  },
  "collection_meta": {
    "collection_date": "2026-05-04",
    "phase": "phase3_enriched",
    "data_sources": [
      "wikipedia",
      "wikidata",
      "official_website",
      "news_search",
      "web_search"
    ],
    "completeness_score": 84,
    "notes": "骨架文件中原始数据为MBN的误识别，已全面修正为Seoul Broadcasting System (SBS)的正确信息。排除了错误的别名'Music Business Norway'。",
    "quotes": [
      {
        "title": "Seoul Broadcasting System - English Wikipedia",
        "url": "https://en.wikipedia.org/wiki/Seoul_Broadcasting_System"
      },
      {
        "title": "SBS（韩国）- 中文维基百科",
        "url": "https://zh.wikipedia.org/wiki/SBS_(韩国)"
      },
      {
        "title": "SBS与Netflix签署内容供应协议",
        "url": "https://pulse.mk.co.kr/news/english/11201202"
      },
      {
        "title": "SBS与新加坡IMDA签署联合制作协议",
        "url": "https://www.asiaone.com/singapore/dramas-variety-shows-imda-and-south-koreas-sbs-formalise-partnership-co-produce-content"
      },
      {
        "title": "SBS 2026年电视剧阵容公布",
        "url": "https://www.chosun.com/english/kpop-culture-en/2026/02/10/4JK4I55BUJG2BNYJFZKYZ35J4I/"
      },
      {
        "title": "SBS对AI训练使用新闻数据收费",
        "url": "https://www.koreaherald.com/article/10572608"
      },
      {
        "title": "SBS世界杯转播权谈判破裂",
        "url": "https://www.mk.co.kr/en/hot-issues/12024191"
      },
      {
        "title": "方文信SBS社长简介",
        "url": "https://ko.wikipedia.org/wiki/방문신"
      },
      {
        "title": "SBS官方网站",
        "url": "https://www.sbs.co.kr"
      }
    ]
  }
}