{
  "org_id": "KR-NGO-007",
  "basic_info": {
    "name_original": "민주사회를 위한 변호사모임",
    "name_zh": "民主社会律师协会",
    "name_en": "Minbyun - Lawyers for a Democratic Society",
    "aliases": [
      "민변",
      "Minbyun",
      "民主辩"
    ],
    "org_type": "NGO",
    "org_subtype": null,
    "country_iso3": "KOR",
    "hq_country_iso3": "KOR",
    "founded_date": "1988-05-25",
    "website": "https://www.minbyun.or.kr/"
  },
  "social_accounts": [
    {
      "platform": "facebook",
      "account_name": "민주사회를 위한 변호사모임 - 민변, Minbyun",
      "url": "https://www.facebook.com/minbyunkorea/",
      "source": "Facebook"
    },
    {
      "platform": "twitter_x",
      "account_name": "@minbyun",
      "url": "https://x.com/minbyun",
      "source": "X"
    },
    {
      "platform": "youtube",
      "account_name": "민변",
      "url": "https://www.youtube.com/@minbyun1988/videos",
      "source": "YouTube"
    }
  ],
  "digital_assets": [
    {
      "name": "Minbyun官方网站",
      "url": "https://www.minbyun.or.kr/",
      "description": "民主社会律师协会官方网站",
      "source": "Wikipedia"
    },
    {
      "name": "Minbyun英文页面",
      "url": "https://www.minbyun.or.kr/?cat=2188",
      "description": "民主社会律师协会英文介绍页面",
      "source": "Minbyun"
    }
  ],
  "key_people": [
    {
      "person_id": "KR-PERSON-000492",
      "name": "尹福男 (Yun Bok-nam)",
      "title": "会长 (President)",
      "title_description": "民主社会律师协会最高负责人",
      "description": "现任民变会长，领导该组织开展法律倡导活动"
    },
    {
      "person_id": "KR-PERSON-000493",
      "name": "李在明 (Lee Jae-myung)",
      "title": "会员 (Member)",
      "title_description": "民变会员律师，第21任韩国总统（2026年当选）",
      "description": "民变出身的政治人物，继卢武铉、文在寅之后第三位成为总统的民变会员"
    },
    {
      "person_id": "KR-PERSON-000494",
      "name": "赵永善 (Cho Young-sun)",
      "title": "法定代表人 (Legal Representative)",
      "title_description": "民变的法定登记代表",
      "description": "负责组织法律事务"
    }
  ],
  "departments": [
    {
      "name": "公益人权辩护中心 (Public Interest & Human Rights Litigation Center)",
      "description": "专门处理公益诉讼与人权案件",
      "dept_id": "KR-NGO-007-DEPT-001"
    },
    {
      "name": "司法中心 (Judicial Center)",
      "description": "关注司法改革与法治建设",
      "dept_id": "KR-NGO-007-DEPT-002"
    },
    {
      "name": "16个专门委员会",
      "description": "涵盖各人权领域的专门委员会，包括劳动、性别、环境、难民等",
      "dept_id": "KR-NGO-007-DEPT-003"
    }
  ],
  "recent_events": [
    {
      "date": "2025-12-08",
      "title": "民变举办2025年韩国人权报告大会",
      "description": "民变在世界人权宣言日前举办年度人权报告大会，记录韩国社会民主与人权状况，重点讨论戒严事件与内乱审判现状",
      "impact": "为韩国人权状况提供年度独立评估",
      "source": "https://minbyun.s3.ap-northeast-2.amazonaws.com/wp-content/uploads/2025/12/08183455/M20251208_사후-보도자료_민변-2025년-한국인권보고대회-개최-2.pdf"
    },
    {
      "date": "2026-05-04",
      "title": "民变向李在明政府提出政策建议",
      "description": "民变向新就任的李在明政府发出呼吁，要求'终结内乱、改革检察机关、制定反歧视法'等落实市民命令",
      "impact": "对新一届政府的司法改革议程产生直接影响",
      "source": "https://www.msn.com/ko-kr/정치/정부기관/민변-이재명-향해-내란-종식-검찰-개혁-시민-명령-실천해야-이재명-정부/ar-AA1G3005"
    },
    {
      "date": "2025-12-10",
      "title": "民变会员李在明当选第21任总统",
      "description": "民变会员李在明当选韩国第21任总统，使民变成为继产出卢武铉（第16任）、文在寅（第19任）之后第三位总统的法律团体",
      "impact": "民变在韩国政坛的影响力达到新高度",
      "source": "https://namu.wiki/w/%EB%AF%BC%EC%A3%BC%EC%82%AC%ED%9A%8C%EB%A5%BC%20%EC%9C%84%ED%95%9C%20%EB%B3%80%ED%98%B8%EC%82%AC%EB%AA%A8%EC%9E%84"
    }
  ],
  "related_entities": [
    {
      "org_id": "KR-GOV-001",
      "org_name": "韩国总统室 (Office of the President of the Republic of Korea)",
      "org_type": "GOV",
      "org_description": "韩国总统室，多位民变会员曾任总统",
      "relationship_type": "affiliated"
    },
    {
      "org_id": "KR-IGO-001",
      "org_name": "UN ECOSOC",
      "org_type": "IGO",
      "org_description": "联合国经济及社会理事会，民变拥有特别谘商地位",
      "relationship_type": "affiliated"
    },
    {
      "org_id": "KR-NGO-004",
      "org_name": "People's Solidarity for Participatory Democracy",
      "org_type": "NGO",
      "org_description": "参与连带，与民变同为进步派公民团体",
      "relationship_type": "partner"
    }
  ],
  "core_business": "民主社会律师协会（Minbyun/民变）是韩国进步派律师团体，成立于1988年5月25日（全斗焕军政府垮台一年后）。该组织旨在通过司法与立法手段解决韩国社会不平等问题，通过诉讼、研究、调查促进韩国民主发展。民变拥有8个地方分支和16个专门委员会，涵盖人权各领域。该组织以会员会费运营，会员包括律师、法学教授、法学生在读或结业者及各地干事。著名会员包括卢武铉（第16任总统）、朴元淳（首尔市长）、文在寅（第19任总统）和李在明（第21任总统）。民变在韩国公益诉讼领域发挥核心作用，推动了堕胎法废除、替代役制度等宪法案件。",
  "industries": [],
  "apec_stance": "民变作为法律倡导组织，不直接参与APEC事务，但在人权与法治领域关注国际贸易协定中的劳工权利与环境保护条款。",
  "profile": "民主社会律师协会（Min变/Minbyun）成立于1988年5月25日，是韩国最具影响力的进步派法律团体。全称为'民主社会为之辩护律师聚会'，简称'民变'。该组织在军政府倒台后由进步律师组建，以诉讼、研究、调查为手段推动民主与人权。拥有8个地方分支和16个专门委员会，以会员会费独立运营。民变已产生三位韩国总统：卢武铉、文在寅、李在明（2026年当选），以及首尔市长朴元淳等重要政治人物。在公益诉讼领域成就卓著，包括推动堕胎法违宪判决、替代役制度确立等里程碑案件。拥有联合国经社理事会特别谘商地位。",
  "collection_meta": {
    "collection_date": "2026-05-05",
    "phase": "phase3_enrichment",
    "data_sources": [
      "Wikipedia EN - Minbyun",
      "Wikipedia KO - 민주사회를 위한 변호사모임",
      "Minbyun Official Website",
      "NamuWiki",
      "Law Leader"
    ],
    "completeness_score": 90,
    "notes": "Enriched with comprehensive data. Minbyun has produced 3 presidents including the newly elected Lee Jae-myung (2026)."
  }
}