{
  "org_id": "KR-NGO-006",
  "basic_info": {
    "name_original": "경제정의실천시민연합",
    "name_zh": "经济正义实践市民联合",
    "name_en": "Citizens' Coalition for Economic Justice (CCEJ)",
    "aliases": [
      "경실련",
      "CCEJ"
    ],
    "org_type": "NGO",
    "org_subtype": null,
    "country_iso3": "KOR",
    "hq_country_iso3": "KOR",
    "founded_date": "1989-07-08",
    "website": "https://ccej.or.kr/"
  },
  "social_accounts": [],
  "digital_assets": [
    {
      "name": "CCEJ官方网站",
      "url": "https://ccej.or.kr/",
      "description": "经济正义实践市民联合官方网站",
      "source": "Wikipedia"
    }
  ],
  "key_people": [
    {
      "person_id": "KR-PERSON-000915",
      "name": "柳仲锡 (Joongseok Joseph Ryu)",
      "title": "共同代表 (Co-representative)",
      "title_description": "负责组织战略方向，任期至2026年2月",
      "description": "经济学家，担任CCEJ共同代表约4年"
    },
    {
      "person_id": null,
      "name": null,
      "title": "共同代表 (Co-representative)",
      "title_description": "2026年新任共同代表，在2026年4月就职典礼上就任",
      "description": "2026年春季就任的新任共同代表"
    }
  ],
  "departments": [],
  "recent_events": [
    {
      "date": "2026-05-04",
      "title": "CCEJ设计AI市民参与平台",
      "description": "CCEJ正在设计AI市民参与平台，探索人工智能时代公民社会如何捍卫公共利益的新路径",
      "impact": "推动公民社会在AI时代的创新参与模式",
      "source": "https://en.sedaily.com/news/2026/05/04/ai-era-who-will-defend-the-public-interest-civil-societys"
    },
    {
      "date": "2026-02-25",
      "title": "CCEJ审查广域整合法案发现99条有毒条款",
      "description": "CCEJ举行记者会公布对三项行政整合特别法案的全面审查结果，发现99条有害条款",
      "impact": "对行政区域整合法案提出重要修正意见",
      "source": "https://biz.chosun.com/en/en-society/2026/02/25/HQMCG3XIWRDEDPWDJQQWMDFRWE/"
    },
    {
      "date": "2026-03-31",
      "title": "CCEJ发布广域议员海外出差调查报告",
      "description": "CCEJ发布全国17个广域议会海外出差实态调查结果，发现海外出差花费达128亿韩元，报告公开率仅16%",
      "impact": "推动地方议会透明度改革",
      "source": "http://m.breaknews.com/1196472"
    },
    {
      "date": "2026-04-21",
      "title": "CCEJ举行共同代表就职典礼暨春季后援会",
      "description": "CCEJ在首尔文学之家举行新任共同代表就职典礼及春季后援会活动",
      "impact": "领导层换届，延续经济正义运动",
      "source": "https://ccej.or.kr/"
    }
  ],
  "related_entities": [
    {
      "org_id": "KR-NGO-004",
      "org_name": "People's Solidarity for Participatory Democracy",
      "org_type": "NGO",
      "org_description": "参与连带，韩国三大市民团体之一",
      "relationship_type": "partner"
    },
    {
      "org_id": "KR-NGO-005",
      "org_name": "韩国环境运动联合会 (Korean Federation for Environmental Movement)",
      "org_type": "NGO",
      "org_description": "韩国环境运动联合会，韩国三大市民团体之一",
      "relationship_type": "partner"
    },
    {
      "org_id": "KR-IGO-001",
      "org_name": "UN ECOSOC",
      "org_type": "IGO",
      "org_description": "联合国经济及社会理事会，CCEJ于1999年获特别谘商地位",
      "relationship_type": "affiliated"
    },
    {
      "org_id": "KR-NGO-012",
      "org_name": "Right Livelihood Award Foundation",
      "org_type": "NGO",
      "org_description": "正确生活方式奖基金会，CCEJ于2003年获该奖",
      "relationship_type": "affiliated"
    }
  ],
  "core_business": "经济正义实践市民联合（CCEJ）成立于1989年7月8日，是韩国首个真正意义上的市民运动组织，也是韩国三大市民团体之一（与参与连带、环境运动联合会并列）。CCEJ致力于通过和平的市民运动实现经济正义与社会正义，推动民主福利社会建设。该组织拥有35个支部和约35,000名会员。CCEJ在消除不平等方面取得显著成就，1993年推动金融实名制实施，2003年获得正确生活方式奖（Right Livelihood Award，又称'另类诺贝尔奖'）。1999年获得联合国经社理事会特别谘商地位。当前重点关注财阀改革、经济民主化、AI时代公共利益保护等议题。",
  "industries": [],
  "apec_stance": "CCEJ关注APEC框架下的经济正义议题，包括贸易自由化对韩国经济的影响、财阀制度改革、经济民主化等。",
  "profile": "经济正义实践市民联合（CCEJ，简称经实联）成立于1989年7月8日，是韩国首个市民运动组织，由市民自发组建以推动基于公平收入分配的经济正义实现。经实联是韩国三大市民团体之一，拥有35个支部和约35,000名会员。历史成就包括推动1993年金融实名制、反对不动产投机、推动经济民主化改革。2003年获正确生活方式奖。1999年获联合国经社理事会特别谘商地位。当前关注领域包括AI时代公共利益、行政区域整合监督、地方议会透明度等。CCEJ还运营经济正义研究所进行政策研究。",
  "collection_meta": {
    "collection_date": "2026-05-05",
    "phase": "phase3_enrichment",
    "data_sources": [
      "Wikipedia EN - Citizens' Coalition for Economic Justice",
      "Wikipedia KO - 경제정의실천시민연합",
      "CCEJ Official Website",
      "Chosun Biz",
      "SE Daily"
    ],
    "completeness_score": 88,
    "notes": "Enriched with Wikipedia data, current leadership transition, and 2025-2026 activities."
  }
}