{
  "person_id": "MY-PERSON-000294",
  "wikidata_qid": "Q115567056",
  "name": "扎丽哈·宾蒂·穆斯塔法",
  "name_zh": "扎丽哈·穆斯塔法",
  "name_en": "Zaliha binti Mustafa",
  "aliases": [
    "Datuk Seri Dr. Zaliha Mustafa",
    "Dr Zaliha",
    "Dr Z"
  ],
  "nationality": "MY",
  "gender": "female",
  "birth_date": "1964-06-28",
  "birth_place": "马来西亚柔佛州新山",
  "contacts": [
    {
      "type": "phone",
      "value": "03-88923652",
      "source": "马来西亚国会官方网站"
    },
    {
      "type": "fax",
      "value": "03-88880375",
      "source": "马来西亚国会官方网站"
    },
    {
      "type": "email",
      "value": "zaliha@jpm.gov.my",
      "source": "马来西亚国会官方网站"
    },
    {
      "type": "website",
      "value": "https://drzaliha.my",
      "source": "个人官方网站"
    }
  ],
  "current_positions": [
    "下议院议员（Sekijang）",
    "政府后座议员俱乐部（BBC）主席",
    "国会公共账目委员会（PAC）成员"
  ],
  "education": [
    {
      "start_date": "1970s",
      "end_date": "1980",
      "institution": "苏丹易卜拉欣女子学校（SIGS），柔佛新山",
      "degree": "primary",
      "field": "基础教育"
    },
    {
      "start_date": "1981",
      "end_date": "1982",
      "institution": "MARA初级理学院（MRSM）哥打巴鲁，吉兰丹",
      "degree": "high_school",
      "field": "理科"
    },
    {
      "start_date": "1982",
      "end_date": "1983",
      "institution": "MARA初级理学院（MRSM）芙蓉，森美兰",
      "degree": "high_school",
      "field": "大学预科（Matrikulasi）"
    },
    {
      "start_date": "1983",
      "end_date": null,
      "institution": "马来西亚国民大学（UKM）医学院",
      "degree": "bachelor",
      "field": "医学与外科学（MD）"
    }
  ],
  "work_experience": [
    {
      "start_date": "1989",
      "end_date": "1990",
      "organization": "苏丹后阿米娜医院（HSA），柔佛新山",
      "org_id": null,
      "position": "研究生医生"
    },
    {
      "start_date": "1990",
      "end_date": "1990",
      "organization": "彭亨州淡马鲁县医院",
      "org_id": null,
      "position": "医疗官"
    },
    {
      "start_date": "1991",
      "end_date": "1993",
      "organization": "霹雳州太平县医院",
      "org_id": null,
      "position": "医疗官"
    },
    {
      "start_date": "1993",
      "end_date": null,
      "organization": "Penawar医疗集团",
      "org_id": null,
      "position": "医疗官"
    },
    {
      "start_date": null,
      "end_date": "2022",
      "organization": "慕尼诊所（Klinik Murni），柔佛古来",
      "org_id": null,
      "position": "医生及诊所业主"
    },
    {
      "start_date": "2018",
      "end_date": "2020",
      "organization": "妇女、家庭及社区发展部",
      "org_id": "MY-GOV-014",
      "position": "政治秘书（服务于部长旺阿兹莎）"
    },
    {
      "start_date": "2022-11-19",
      "end_date": null,
      "organization": "马来西亚下议院",
      "org_id": "MY-GOV-019",
      "position": "下议院议员（Sekijang）"
    },
    {
      "start_date": "2022-12-03",
      "end_date": "2023-12-12",
      "organization": "马来西亚卫生部",
      "org_id": "MY-GOV-008",
      "position": "卫生部长"
    },
    {
      "start_date": "2023-12-12",
      "end_date": "2025-12-17",
      "organization": "首相署（联邦直辖区事务）",
      "org_id": "MY-GOV-001",
      "position": "首相署部长（联邦直辖区）"
    },
    {
      "start_date": "2026-01-22",
      "end_date": null,
      "organization": "政府后座议员俱乐部（BBC）",
      "org_id": null,
      "position": "主席"
    },
    {
      "start_date": "2026-01-26",
      "end_date": null,
      "organization": "国会公共账目委员会（PAC）",
      "org_id": null,
      "position": "委员"
    }
  ],
  "person_relationships": [
    {
      "person_id": null,
      "person_name": "旺阿兹莎·旺伊斯迈",
      "relationship_type": "superior",
      "description": "曾任旺阿兹莎（时任副首相兼妇女部长）的政治秘书"
    },
    {
      "person_id": null,
      "person_name": "安华·易卜拉欣",
      "relationship_type": "superior",
      "description": "安华委任其为卫生部长和首相署部长"
    },
    {
      "person_id": null,
      "person_name": "哈丽玛·雅各布",
      "relationship_type": "colleague",
      "description": "同为内阁中的女性部长，共同推动女性议题"
    }
  ],
  "social_accounts": [
    {
      "platform": "facebook",
      "account_name": "Dr Zaliha Mustafa",
      "url": "https://www.facebook.com/dr.zalihasekijang/",
      "source": "马来西亚国会官方网站"
    },
    {
      "platform": "twitter",
      "account_name": "@Zaliha_DrZ",
      "url": "https://x.com/DrZalihaMustafa",
      "source": "马来西亚国会官方网站"
    },
    {
      "platform": "instagram",
      "account_name": "drzalihamustafa",
      "url": "https://www.instagram.com/drzalihamustafa/",
      "source": "Instagram平台"
    },
    {
      "platform": "tiktok",
      "account_name": "drzalihamustafa",
      "url": "https://www.tiktok.com/@drzalihamustafa",
      "source": "TikTok平台"
    },
    {
      "platform": "website",
      "account_name": "YB Dr Zaliha Mustafa",
      "url": "https://drzaliha.my",
      "source": "个人官方网站"
    },
    {
      "platform": "website",
      "account_name": "Linktree",
      "url": "https://linktr.ee/drzalihamustafa",
      "source": "社交媒体链接汇总"
    }
  ],
  "family_members": [
    {
      "person_id": null,
      "name": "阿末·阿兹兰医生（Dr. Ahmad Adzlan）",
      "relationship": "spouse",
      "industry_or_organization": "医学"
    }
  ],
  "political_stances": [
    "支持马来西亚MADANI政府议程",
    "关注医疗体系改革，曾推动解决合约医生问题",
    "关注联邦直辖区（吉隆坡、布城、纳闽）发展与繁荣",
    "重视公共卫生和基层医疗服务"
  ],
  "major_achievements": [
    {
      "date": "2022-12-03",
      "organization": "马来西亚卫生部",
      "achievement": "成为马来西亚历史上首位女性卫生部长"
    },
    {
      "date": "2023-12-12",
      "organization": "首相署",
      "achievement": "成为首位女性首相署部长（联邦直辖区事务）"
    },
    {
      "date": "2023-10-05",
      "organization": "马来西亚国民大学（UKM）医学院",
      "achievement": "获颁2023年UKM医学院杰出校友奖"
    },
    {
      "date": "2025-03-07",
      "organization": "马来西亚联邦直辖区",
      "achievement": "获封联邦直辖区王冠勋章（P.M.W.），受封Datuk Seri勋衔"
    },
    {
      "date": "2026-01-22",
      "organization": "马来西亚下议院",
      "achievement": "被任命为政府后座议员俱乐部（BBC）主席"
    },
    {
      "date": "2026-01-26",
      "organization": "马来西亚下议院",
      "achievement": "被任命为国会公共账目委员会（PAC）委员"
    }
  ],
  "biography_summary": "拿督斯里扎丽哈·宾蒂·穆斯塔法医生，1964年6月28日出生于柔佛州新山，马来西亚政治人物及医生。她毕业于马来西亚国民大学（UKM）医学院，曾在多家公立医院担任医疗官，后在柔佛古来经营私人诊所。1999年加入国民公正党（PKR），历任PKR柔佛州妇女组主席（1990年）、妇女组副主席（2007-2009年）、公正党学院院长（2009年）、中央领导理事会成员（2018-2020年）、选举委员会主席等要职。2022年11月首次当选Sekijang国会议员，随后被首相安华委任为卫生部长，成为马来西亚首位女性卫生部长（2022-2023）。2023年12月内阁改组后转任首相署部长（联邦直辖区事务），同样为首位担任此职的女性。2025年12月内阁改组中卸任部长。2026年1月被任命为政府后座议员俱乐部（BBC）主席及国会公共账目委员会（PAC）委员。已婚，丈夫为阿末·阿兹兰医生，育有四名子女。",
  "profile": {
    "source_url": "https://upload.wikimedia.org/wikipedia/commons/thumb/c/cf/Zaliha_Mustafa_in_July_2025.jpg/250px-Zaliha_Mustafa_in_July_2025.jpg",
    "local_path": null
  },
  "collection_meta": {
    "collection_date": "2026-04-21",
    "phase": "phase4_person_profile_enriched",
    "data_sources": [
      "wikipedia",
      "mymp.org.my",
      "drzaliha.my",
      "parlimen.gov.my",
      "mywilayah.com",
      "malaymail.com",
      "nst.com.my",
      "bernama.com",
      "thevibes.com",
      "theedgemalaysia.com"
    ],
    "completeness_score": 85,
    "notes": "扎丽哈·穆斯塔法，PKR成员，Sekijang国会议员。马来西亚首位女性卫生部长（2022-2023）及首位女性首相署部长（联邦直辖区，2023-2025）。2025年12月内阁改组卸任，2026年1月被任命为政府后座议员俱乐部（BBC）主席及公共账目委员会（PAC）委员。完整档案涵盖教育、职业、政党履历、家庭、社会媒体及主要成就。"
  }
}
