{
  "person_id": "MY-PERSON-000298",
  "wikidata_qid": "Q39050368",
  "name": "赛沙迪",
  "name_zh": "赛沙迪",
  "name_en": "Syed Saddiq Syed Abdul Rahman",
  "aliases": ["Syed Saddiq", "Syed Saddiq bin Syed Abdul Rahman"],
  "nationality": "MY",
  "gender": "male",
  "birth_date": "1992-12-06",
  "birth_place": "马来西亚柔佛州巴西（Pulai, Johor Bahru, Johor）",
  "contacts": [
    {
      "type": "email",
      "value": "syedsaddiq92@gmail.com",
      "source": "马来西亚议会官网 / Wikidata"
    },
    {
      "type": "website",
      "value": "https://syedsaddiq.my",
      "source": "Wikidata"
    },
    {
      "type": "website",
      "value": "http://www.parlimen.gov.my/profile-ahli.html?uweb=dr&id=4185",
      "source": "马来西亚议会官网"
    }
  ],
  "current_positions": [
    "下议院议员（Muar选区）",
    "统民党（MUDA）党员"
  ],
  "education": [
    {
      "start_date": null,
      "end_date": null,
      "institution": "皇家军事学院（Royal Military College, RMC）",
      "degree": null,
      "field": "中学教育"
    },
    {
      "start_date": null,
      "end_date": null,
      "institution": "马来西亚国际伊斯兰大学（International Islamic University Malaysia, IIUM）",
      "degree": "法学学士（LLB）",
      "field": "法律"
    },
    {
      "start_date": "2021-01",
      "end_date": "2021-04",
      "institution": "新加坡国立大学李光耀公共政策学院",
      "degree": "李光耀公共服务高级研究员",
      "field": "公共政策"
    }
  ],
  "work_experience": [
    {
      "start_date": "2015",
      "end_date": "2015",
      "organization": "马来西亚总理署",
      "org_id": "MY-GOV-019",
      "position": "首相署部长南希·舒克里之Perdana Fellow"
    },
    {
      "start_date": "2016-09",
      "end_date": "2020-05",
      "organization": "土著团结党（BERSATU）",
      "org_id": null,
      "position": "青年团（ARMADA）创始团长"
    },
    {
      "start_date": "2018-05-09",
      "end_date": null,
      "organization": "马来西亚下议院",
      "org_id": "MY-GOV-019",
      "position": "下议院议员（Muar选区）"
    },
    {
      "start_date": "2018-07-02",
      "end_date": "2020-02-24",
      "organization": "马来西亚青年及体育部",
      "org_id": "MY-GOV-019",
      "position": "青年及体育部长"
    },
    {
      "start_date": "2020-09-17",
      "end_date": "2023-11-09",
      "organization": "统民党（MUDA）",
      "org_id": null,
      "position": "创始主席"
    }
  ],
  "person_relationships": [
    {
      "person_id": null,
      "person_name": "Bella Astillah",
      "relationship_type": "spouse",
      "description": "马来西亚歌手兼演员，2026年3月28日与赛沙迪订婚"
    },
    {
      "person_id": null,
      "person_name": "马哈蒂尔·穆罕默德（Mahathir Mohamad）",
      "relationship_type": "mentor",
      "description": "前首相，任命赛沙迪为青年及体育部长，政治导师"
    },
    {
      "person_id": null,
      "person_name": "慕尤丁·雅辛（Muhyiddin Yassin）",
      "relationship_type": "political_rival",
      "description": "土著团结党主席，赛沙迪2020年被其开除出党"
    },
    {
      "person_id": null,
      "person_name": "Amira Aisya Abdul Aziz",
      "relationship_type": "colleague",
      "description": "MUDA副主席，赛沙迪辞职后接任代理主席"
    },
    {
      "person_id": null,
      "person_name": "Abe Lim Hooi Sean",
      "relationship_type": "associate",
      "description": "律师，赛沙迪前女友，曾以MUDA候选人身份参加2023年雪兰莪州选举"
    },
    {
      "person_id": null,
      "person_name": "Wan Ahmad Fayhsal Wan Ahmad Kamal",
      "relationship_type": "political_rival",
      "description": "接替赛沙迪成为BERSATU青年团团长"
    },
    {
      "person_id": null,
      "person_name": "安华·易卜拉欣（Anwar Ibrahim）",
      "relationship_type": "political_rival",
      "description": "赛沙迪在2023年撤回对其政府支持"
    }
  ],
  "social_accounts": [
    {
      "platform": "Instagram",
      "account_name": "syedsaddiq",
      "url": "https://www.instagram.com/syedsaddiq/",
      "source": "Wikidata / Instagram"
    },
    {
      "platform": "X (Twitter)",
      "account_name": "SyedSaddiq",
      "url": "https://x.com/SyedSaddiq",
      "source": "Wikidata"
    },
    {
      "platform": "TikTok",
      "account_name": "syedsaddiq",
      "url": "https://www.tiktok.com/@syedsaddiq",
      "source": "TikTok"
    },
    {
      "platform": "Facebook",
      "account_name": "syedsaddiqofficial",
      "url": "https://www.facebook.com/syedsaddiqofficial/",
      "source": "Facebook"
    },
    {
      "platform": "Threads",
      "account_name": "syedsaddiq",
      "url": "https://www.threads.com/@syedsaddiq",
      "source": "Wikidata"
    }
  ],
  "family_members": [
    {
      "person_id": null,
      "name": "Syed Abdul Rahman（父亲）",
      "relationship": "父亲",
      "industry_or_organization": "新加坡籍阿拉伯裔马来人，前新加坡建筑工人"
    },
    {
      "person_id": null,
      "name": "（母亲，姓名不详）",
      "relationship": "母亲",
      "industry_or_organization": "前英语教师"
    }
  ],
  "political_stances": [
    "支持巴勒斯坦，批评以色列的非法占领行为",
    "倡导将投票年龄从21岁降至18岁（Undi18运动）",
    "主张多族群、以青年为中心的政治改革",
    "反对国会议员不公平的财政拨款分配",
    "呼吁改革内阁部长和国会议员的养老金制度",
    "支持反腐败和政府透明度改革"
  ],
  "major_achievements": [
    {
      "date": "2016",
      "organization": "亚洲英国议会制辩论锦标赛",
      "achievement": "三次获得亚洲最佳辩手称号"
    },
    {
      "date": "2016",
      "organization": "联合亚洲辩论锦标赛（UADC）",
      "achievement": "获得联合亚洲辩论锦标赛冠军"
    },
    {
      "date": "2018-05-09",
      "organization": "马来西亚下议院",
      "achievement": "以25岁之龄当选为最年轻的国会议员之一，当选Muar选区议员"
    },
    {
      "date": "2018-07",
      "organization": "马来西亚联邦政府",
      "achievement": "以25岁之龄成为马来西亚历史上最年轻的联邦部长（青年及体育部长）"
    },
    {
      "date": "2019-07-16",
      "organization": "马来西亚下议院",
      "achievement": "成功推动宪法修正案，将投票年龄降至18岁（Undi18），获全票通过"
    },
    {
      "date": "2020-09-17",
      "organization": "统民党（MUDA）",
      "achievement": "创立马来西亚首个多元种族、以青年为核心的新政党MUDA"
    },
    {
      "date": "2021",
      "organization": "NONA超级英雄奖",
      "achievement": "获得NONA Man Inspiring Award"
    },
    {
      "date": "2025-06-25",
      "organization": "马来西亚上诉法院",
      "achievement": "上诉法院推翻其所有贪腐定罪，宣判无罪释放"
    }
  ],
  "biography_summary": "赛沙迪（Syed Saddiq Syed Abdul Rahman，1992年12月6日生于柔佛州巴西），马来西亚政治人物，现任下议院Muar选区议员。他是统民党（MUDA）的创始人和前主席，此前为土著团结党（BERSATU）创始成员及青年团团长。2018年以25岁之龄当选国会议员并被任命为青年及体育部长，成为马来西亚历史上最年轻的联邦部长。任内成功推动Undi18宪法修正案，将投票年龄从21岁降至18岁。2020年被BERSATU开除后创立MUDA。2023年因贪腐指控被高等法院定罪判刑7年，但2025年6月上诉法院推翻定罪，宣判无罪释放。他活跃于社交媒体，在Instagram拥有超过200万粉丝，以敢于发声著称，积极倡导青年参政、反腐败和政府透明度改革。",
  "profile": {
    "source_url": "https://upload.wikimedia.org/wikipedia/commons/thumb/8/80/Syed_Saddiq_%28cropped%29.jpg/250px-Syed_Saddiq_%28cropped%29.jpg",
    "local_path": null
  },
  "collection_meta": {
    "collection_date": "2026-04-21",
    "phase": "phase4_person_profile",
    "data_sources": [
      "wikipedia",
      "wikidata",
      "instagram",
      "tiktok",
      "facebook",
      "parlimen.gov.my"
    ],
    "completeness_score": 88,
    "notes": "赛沙迪，统民党（MUDA）创始人及前主席，现任Muar选区国会议员。马来西亚历史上最年轻的联邦部长（25岁）。2025年6月上诉法院推翻贪腐定罪。2026年3月与歌手Bella Astillah订婚。档案基于Wikipedia、Wikidata及多个社交媒体来源综合整理。"
  }
}