{
  "wikidata": {
    "pageid": 96902992,
    "ns": 0,
    "title": "Q98703784",
    "lastrevid": 1867447302,
    "modified": "2023-04-03T16:11:45Z",
    "type": "item",
    "id": "Q98703784",
    "labels": {
      "en": {
        "language": "en",
        "value": "Frederick Chew"
      },
      "nl": {
        "language": "nl",
        "value": "Frederick Chew"
      },
      "ast": {
        "language": "ast",
        "value": "Frederick Chew"
      }
    },
    "descriptions": {
      "en": {
        "language": "en",
        "value": "government official"
      }
    },
    "aliases": {},
    "claims": {
      "P31": [
        {
          "mainsnak": {
            "snaktype": "value",
            "property": "P31",
            "hash": "ad7d38a03cdd40cdc373de0dc4e7b7fcbccb31d9",
            "datavalue": {
              "value": {
                "entity-type": "item",
                "numeric-id": 5,
                "id": "Q5"
              },
              "type": "wikibase-entityid"
            },
            "datatype": "wikibase-item"
          },
          "type": "statement",
          "id": "Q98703784$b7c4f2db-42d5-34d0-b22b-354d280509df",
          "rank": "normal"
        }
      ],
      "P21": [
        {
          "mainsnak": {
            "snaktype": "value",
            "property": "P21",
            "hash": "85ad4b1c7348f7a5aac521135040d74e91fb5939",
            "datavalue": {
              "value": {
                "entity-type": "item",
                "numeric-id": 6581097,
                "id": "Q6581097"
              },
              "type": "wikibase-entityid"
            },
            "datatype": "wikibase-item"
          },
          "type": "statement",
          "id": "q98703784$28504c2c-4e7c-590c-3b24-64bb8fb70239",
          "rank": "normal"
        }
      ],
      "P27": [
        {
          "mainsnak": {
            "snaktype": "value",
            "property": "P27",
            "hash": "ce640f712c5a0282080e2cfbccd5a73edfd291e7",
            "datavalue": {
              "value": {
                "entity-type": "item",
                "numeric-id": 334,
                "id": "Q334"
              },
              "type": "wikibase-entityid"
            },
            "datatype": "wikibase-item"
          },
          "type": "statement",
          "id": "q98703784$48cff5c7-4838-563b-2c86-76d7971cc59b",
          "rank": "normal"
        }
      ],
      "P735": [
        {
          "mainsnak": {
            "snaktype": "value",
            "property": "P735",
            "hash": "c5581f6b5373408c1f1302c859047e0b0d52e7e4",
            "datavalue": {
              "value": {
                "entity-type": "item",
                "numeric-id": 3273004,
                "id": "Q3273004"
              },
              "type": "wikibase-entityid"
            },
            "datatype": "wikibase-item"
          },
          "type": "statement",
          "id": "Q98703784$9ece9a52-4167-dadc-b4c0-5432ea90e8be",
          "rank": "normal"
        }
      ],
      "P734": [
        {
          "mainsnak": {
            "snaktype": "value",
            "property": "P734",
            "hash": "848bedbe1c5f5935424e1f8a31ab50cc08f48294",
            "datavalue": {
              "value": {
                "entity-type": "item",
                "numeric-id": 16865547,
                "id": "Q16865547"
              },
              "type": "wikibase-entityid"
            },
            "datatype": "wikibase-item"
          },
          "type": "statement",
          "id": "Q98703784$f5b6dce9-4dcd-fb26-0887-e447f91d9340",
          "rank": "normal"
        }
      ],
      "P69": [
        {
          "mainsnak": {
            "snaktype": "value",
            "property": "P69",
            "hash": "3d7c4ed7d2f6adfc1f946715ca463a4440b3349f",
            "datavalue": {
              "value": {
                "entity-type": "item",
                "numeric-id": 189022,
                "id": "Q189022"
              },
              "type": "wikibase-entityid"
            },
            "datatype": "wikibase-item"
          },
          "type": "statement",
          "qualifiers": {
            "P512": [
              {
                "snaktype": "value",
                "property": "P512",
                "hash": "9c9f9ea9d1e05fe6caa7e649b961fd34967eb8e0",
                "datavalue": {
                  "value": {
                    "entity-type": "item",
                    "numeric-id": 1907867,
                    "id": "Q1907867"
                  },
                  "type": "wikibase-entityid"
                },
                "datatype": "wikibase-item"
              }
            ]
          },
          "qualifiers-order": [
            "P512"
          ],
          "id": "Q98703784$6B2BF410-7A66-4F04-80CC-346F0AEFA28B",
          "rank": "normal",
          "references": [
            {
              "hash": "12a9ae35a89b6990c5c63f5d3b467348cb7d5357",
              "snaks": {
                "P854": [
                  {
                    "snaktype": "value",
                    "property": "P854",
                    "hash": "8626a8b9e821b08193b85fd8011699f22fa50866",
                    "datavalue": {
                      "value": "https://www.a-star.edu.sg/About-A-STAR/corporate-profile/people/frederick-chew",
                      "type": "string"
                    },
                    "datatype": "url"
                  }
                ]
              },
              "snaks-order": [
                "P854"
              ]
            }
          ]
        },
        {
          "mainsnak": {
            "snaktype": "value",
            "property": "P69",
            "hash": "9f004befeb4a99d0090def3d794ba9603550b79c",
            "datavalue": {
              "value": {
                "entity-type": "item",
                "numeric-id": 41506,
                "id": "Q41506"
              },
              "type": "wikibase-entityid"
            },
            "datatype": "wikibase-item"
          },
          "type": "statement",
          "qualifiers": {
            "P512": [
              {
                "snaktype": "value",
                "property": "P512",
                "hash": "defc2e1dea583f7dcb97f19747f9e1c2598a44a4",
                "datavalue": {
                  "value": {
                    "entity-type": "item",
                    "numeric-id": 6785253,
                    "id": "Q6785253"
                  },
                  "type": "wikibase-entityid"
                },
                "datatype": "wikibase-item"
              }
            ]
          },
          "qualifiers-order": [
            "P512"
          ],
          "id": "Q98703784$12a8a68f-4b91-72ac-166f-5ecfa92b2f7c",
          "rank": "normal",
          "references": [
            {
              "hash": "12a9ae35a89b6990c5c63f5d3b467348cb7d5357",
              "snaks": {
                "P854": [
                  {
                    "snaktype": "value",
                    "property": "P854",
                    "hash": "8626a8b9e821b08193b85fd8011699f22fa50866",
                    "datavalue": {
                      "value": "https://www.a-star.edu.sg/About-A-STAR/corporate-profile/people/frederick-chew",
                      "type": "string"
                    },
                    "datatype": "url"
                  }
                ]
              },
              "snaks-order": [
                "P854"
              ]
            }
          ]
        }
      ],
      "P108": [
        {
          "mainsnak": {
            "snaktype": "value",
            "property": "P108",
            "hash": "973660d1158e5c3f3a00bf3ea603414809004eb6",
            "datavalue": {
              "value": {
                "entity-type": "item",
                "numeric-id": 1101188,
                "id": "Q1101188"
              },
              "type": "wikibase-entityid"
            },
            "datatype": "wikibase-item"
          },
          "type": "statement",
          "qualifiers": {
            "P39": [
              {
                "snaktype": "value",
                "property": "P39",
                "hash": "bafadc40c39053d643ddfcbb9283494556bf1417",
                "datavalue": {
                  "value": {
                    "entity-type": "item",
                    "numeric-id": 484876,
                    "id": "Q484876"
                  },
                  "type": "wikibase-entityid"
                },
                "datatype": "wikibase-item"
              }
            ],
            "P580": [
              {
                "snaktype": "value",
                "property": "P580",
                "hash": "f9c431990cf525e8469ae480dcad2d9a46c4713d",
                "datavalue": {
                  "value": {
                    "time": "+2019-04-01T00:00:00Z",
                    "timezone": 0,
                    "before": 0,
                    "after": 0,
                    "precision": 11,
                    "calendarmodel": "http://www.wikidata.org/entity/Q1985727"
                  },
                  "type": "time"
                },
                "datatype": "time"
              }
            ]
          },
          "qualifiers-order": [
            "P39",
            "P580"
          ],
          "id": "Q98703784$CF3D095A-1FCF-46C3-BC40-EEF6617F28C9",
          "rank": "normal"
        }
      ],
      "P3052": [
        {
          "mainsnak": {
            "snaktype": "value",
            "property": "P3052",
            "hash": "8c4975ed7a6ce7607289657bfd3b0ccdccb89573",
            "datavalue": {
              "value": "20943264",
              "type": "string"
            },
            "datatype": "external-id"
          },
          "type": "statement",
          "id": "Q98703784$572fca8a-4fdf-fa53-79b6-091aa7ecb960",
          "rank": "normal"
        }
      ],
      "P968": [
        {
          "mainsnak": {
            "snaktype": "value",
            "property": "P968",
            "hash": "80948acf00683688fbebde048f4f1611c5f2b41a",
            "datavalue": {
              "value": "mailto:frederick_chew@a-star.edu.sg",
              "type": "string"
            },
            "datatype": "url"
          },
          "type": "statement",
          "id": "Q98703784$5c742149-450c-a66b-53a8-499c7859e2e6",
          "rank": "normal",
          "references": [
            {
              "hash": "ef95583028bb51e81755294c5b19dc9ce3d8835b",
              "snaks": {
                "P854": [
                  {
                    "snaktype": "value",
                    "property": "P854",
                    "hash": "8329866f63b6a67ce5b78f05244afd94020bf04a",
                    "datavalue": {
                      "value": "https://www.sgdi.gov.sg/ministries/pmo/departments/stppo#Frederick-CHEW_Chief-Public-Sector-Science-Technology-Policy-Plans-Office",
                      "type": "string"
                    },
                    "datatype": "url"
                  }
                ]
              },
              "snaks-order": [
                "P854"
              ]
            }
          ]
        }
      ],
      "P973": [
        {
          "mainsnak": {
            "snaktype": "value",
            "property": "P973",
            "hash": "c8216a88446381492f60c1f231f7c2654eab082e",
            "datavalue": {
              "value": "https://www.tatlerasia.com/people/frederick",
              "type": "string"
            },
            "datatype": "url"
          },
          "type": "statement",
          "qualifiers": {
            "P407": [
              {
                "snaktype": "value",
                "property": "P407",
                "hash": "daf1c4fcb58181b02dff9cc89deb084004ddae4b",
                "datavalue": {
                  "value": {
                    "entity-type": "item",
                    "numeric-id": 1860,
                    "id": "Q1860"
                  },
                  "type": "wikibase-entityid"
                },
                "datatype": "wikibase-item"
              }
            ]
          },
          "qualifiers-order": [
            "P407"
          ],
          "id": "Q98703784$9E8D3DA4-424C-4ADE-AD0B-D19740DA47DD",
          "rank": "normal",
          "references": [
            {
              "hash": "e72621be81b1e1d83fa7365321fe4aef4ca70945",
              "snaks": {
                "P854": [
                  {
                    "snaktype": "value",
                    "property": "P854",
                    "hash": "02a5ca1ce650cf34494a141e10f92623498f9e9f",
                    "datavalue": {
                      "value": "https://www.tatlerasia.com/people/frederick",
                      "type": "string"
                    },
                    "datatype": "url"
                  }
                ],
                "P813": [
                  {
                    "snaktype": "value",
                    "property": "P813",
                    "hash": "6577bcd54cebdf28cae7cc0b7bb7b693de8e3886",
                    "datavalue": {
                      "value": {
                        "time": "+2022-11-03T00:00:00Z",
                        "timezone": 0,
                        "before": 0,
                        "after": 0,
                        "precision": 11,
                        "calendarmodel": "http://www.wikidata.org/entity/Q1985727"
                      },
                      "type": "time"
                    },
                    "datatype": "time"
                  }
                ]
              },
              "snaks-order": [
                "P854",
                "P813"
              ]
            }
          ]
        }
      ],
      "P166": [
        {
          "mainsnak": {
            "snaktype": "value",
            "property": "P166",
            "hash": "356ffa29ea1497898f6fd0692c5350f29fbf1a13",
            "datavalue": {
              "value": {
                "entity-type": "item",
                "numeric-id": 115088775,
                "id": "Q115088775"
              },
              "type": "wikibase-entityid"
            },
            "datatype": "wikibase-item"
          },
          "type": "statement",
          "qualifiers": {
            "P585": [
              {
                "snaktype": "value",
                "property": "P585",
                "hash": "4a6fe7f861358928efef462e361b21704446d129",
                "datavalue": {
                  "value": {
                    "time": "+2021-00-00T00:00:00Z",
                    "timezone": 0,
                    "before": 0,
                    "after": 0,
                    "precision": 9,
                    "calendarmodel": "http://www.wikidata.org/entity/Q1985727"
                  },
                  "type": "time"
                },
                "datatype": "time"
              }
            ]
          },
          "qualifiers-order": [
            "P585"
          ],
          "id": "Q98703784$09857D27-8FE2-4A3E-BDDE-015775369CCF",
          "rank": "normal",
          "references": [
            {
              "hash": "e72621be81b1e1d83fa7365321fe4aef4ca70945",
              "snaks": {
                "P854": [
                  {
                    "snaktype": "value",
                    "property": "P854",
                    "hash": "02a5ca1ce650cf34494a141e10f92623498f9e9f",
                    "datavalue": {
                      "value": "https://www.tatlerasia.com/people/frederick",
                      "type": "string"
                    },
                    "datatype": "url"
                  }
                ],
                "P813": [
                  {
                    "snaktype": "value",
                    "property": "P813",
                    "hash": "6577bcd54cebdf28cae7cc0b7bb7b693de8e3886",
                    "datavalue": {
                      "value": {
                        "time": "+2022-11-03T00:00:00Z",
                        "timezone": 0,
                        "before": 0,
                        "after": 0,
                        "precision": 11,
                        "calendarmodel": "http://www.wikidata.org/entity/Q1985727"
                      },
                      "type": "time"
                    },
                    "datatype": "time"
                  }
                ]
              },
              "snaks-order": [
                "P854",
                "P813"
              ]
            }
          ]
        }
      ],
      "P6424": [
        {
          "mainsnak": {
            "snaktype": "value",
            "property": "P6424",
            "hash": "64a5995f1d7e1a398e66e426284f8052eac913d9",
            "datavalue": {
              "value": "A*Star",
              "type": "string"
            },
            "datatype": "string"
          },
          "type": "statement",
          "id": "Q98703784$59399B9A-272F-4060-BACD-4DEC5DE5B889",
          "rank": "normal",
          "references": [
            {
              "hash": "e72621be81b1e1d83fa7365321fe4aef4ca70945",
              "snaks": {
                "P854": [
                  {
                    "snaktype": "value",
                    "property": "P854",
                    "hash": "02a5ca1ce650cf34494a141e10f92623498f9e9f",
                    "datavalue": {
                      "value": "https://www.tatlerasia.com/people/frederick",
                      "type": "string"
                    },
                    "datatype": "url"
                  }
                ],
                "P813": [
                  {
                    "snaktype": "value",
                    "property": "P813",
                    "hash": "6577bcd54cebdf28cae7cc0b7bb7b693de8e3886",
                    "datavalue": {
                      "value": {
                        "time": "+2022-11-03T00:00:00Z",
                        "timezone": 0,
                        "before": 0,
                        "after": 0,
                        "precision": 11,
                        "calendarmodel": "http://www.wikidata.org/entity/Q1985727"
                      },
                      "type": "time"
                    },
                    "datatype": "time"
                  }
                ]
              },
              "snaks-order": [
                "P854",
                "P813"
              ]
            }
          ]
        }
      ]
    },
    "sitelinks": {}
  },
  "wikipedia": null
}