{
  "org_id": "SG-PARTY-006",
  "basic_info": {
    "name_original": "新加坡民主党",
    "name_zh": "新加坡民主党",
    "name_en": "Singapore Democratic Party",
    "aliases": [
      "SDP",
      "新加坡民主党",
      "Parti Demokratik Singapura"
    ],
    "org_type": "PARTY",
    "org_subtype": "opposition_party",
    "country_iso3": "SGP",
    "hq_country_iso3": "SGP",
    "founded_date": "1980-01-01",
    "website": "http://yoursdp.org/"
  },
  "social_accounts": [
    {
      "platform": "twitter_x",
      "account_name": "yoursdp",
      "url": "https://twitter.com/yoursdp",
      "source": "wikidata"
    },
    {
      "platform": "facebook",
      "account_name": "yoursdp",
      "url": "https://facebook.com/yoursdp",
      "source": "wikidata"
    },
    {
      "platform": "youtube",
      "account_name": "UC_6ZBBzLo-jVQKxlcB8uj_g",
      "url": "https://youtube.com/channel/UC_6ZBBzLo-jVQKxlcB8uj_g",
      "source": "wikidata"
    }
  ],
  "digital_assets": [
    {
      "name": "SDP官方网站",
      "url": "https://yoursdp.org/",
      "description": "新加坡民主党官方网站，包含政策纲领、选举信息和党活动",
      "source": "official_website"
    },
    {
      "name": "SDP GE2025竞选档案",
      "url": "https://yoursdp.org/ge2025/",
      "description": "SDP 2025年大选专区，包含候选人介绍和政策宣言",
      "source": "official_website"
    }
  ],
  "key_people": [
    {
      "person_id": "SG-PERSON-000082",
      "name": "徐順全 (Chee Soon Juan)",
      "title": "Chair",
      "title_description": null,
      "description": null
    }
  ],
  "departments": [
    {
      "dept_id": "SG-PARTY-006-DEPT-001",
      "name": "Central Executive Committee Line-up (2026-2028)",
      "head": null,
      "description": null,
      "parent_dept_id": null
    },
    {
      "dept_id": "SG-PARTY-006-DEPT-002",
      "name": "Leadership",
      "head": null,
      "description": null,
      "parent_dept_id": null
    },
    {
      "dept_id": "SG-PARTY-006-DEPT-003",
      "name": "List of secretaries-general",
      "head": null,
      "description": null,
      "parent_dept_id": null
    },
    {
      "dept_id": "SG-PARTY-006-DEPT-004",
      "name": "List of chairmen",
      "head": null,
      "description": null,
      "parent_dept_id": null
    },
    {
      "dept_id": "SG-PARTY-006-DEPT-005",
      "name": "Former elected Members of Parliament",
      "head": null,
      "description": null,
      "parent_dept_id": null
    },
    {
      "dept_id": "SG-PARTY-006-DEPT-006",
      "name": "Election results",
      "head": null,
      "description": null,
      "parent_dept_id": null
    },
    {
      "dept_id": "SG-PARTY-006-DEPT-007",
      "name": "Parliament",
      "head": null,
      "description": null,
      "parent_dept_id": null
    },
    {
      "dept_id": "SG-PARTY-006-DEPT-008",
      "name": "Seats contested",
      "head": null,
      "description": null,
      "parent_dept_id": null
    },
    {
      "dept_id": "SG-PARTY-006-DEPT-009",
      "name": "By-elections",
      "head": null,
      "description": null,
      "parent_dept_id": null
    },
    {
      "dept_id": "SG-PARTY-006-DEPT-010",
      "name": "References",
      "head": null,
      "description": null,
      "parent_dept_id": null
    }
  ],
  "recent_events": [
    {
      "date": "2025-05-03",
      "title": "GE2025：徐顺全在三巴旺西以46.81%得票率惜败",
      "description": "在2025年全国大选中，SDP秘书长徐顺全在三巴旺西单选区获46.81%选票，以不到1个百分点之差未能获得非选区议员席位。主席保罗·谭比亚在武吉班让单选区参选。SDP连续28年未有民选议员进入国会的记录延续。",
      "impact": "SDP在选举中表现接近突破但仍未能赢得议席，反映反对党竞争格局的变化",
      "source": "https://www.channelnewsasia.com/singapore/ge2025-results-sdp-chee-soon-juan-5107181"
    },
    {
      "date": "2026-02-01",
      "title": "SDP选举产生新一届中委会（2026-2028任期）",
      "description": "SDP选举产生2026-2028任期中央执行委员会，徐顺全继续担任秘书长，保罗·谭比亚继续担任主席。",
      "impact": "SDP领导层保持稳定，为下一阶段政治运作做准备",
      "source": "https://yoursdp.org/ge2025/"
    }
  ],
  "related_entities": [
    {
      "org_id": "SG-PARTY-001",
      "org_name": "People's Action Party (PAP, 人民行动党)",
      "org_type": "PARTY",
      "org_description": "新加坡执政党，SDP的主要政治对手",
      "relationship_type": "strategic_alliance"
    },
    {
      "org_id": "SG-PARTY-004",
      "org_name": "Workers' Party (WP, 工人党)",
      "org_type": "PARTY",
      "org_description": "新加坡主要反对党，与SDP在反对党阵营中共存",
      "relationship_type": "strategic_alliance"
    }
  ],
  "core_business": "新加坡民主党（Singapore Democratic Party，简称SDP）是新加坡的一个中间偏左社会自由主义政党，由詹时中（Chiam See Tong）于1980年8月6日创立。建党宣言提出消除殖民主义和封建主义、维护议会民主、坚持民主和社会主义原则等目标。1984年大选中，詹时中以60.3%得票率当选波东巴西（Potong Pasir）单选区议员，成为新加坡独立后第二位当选反对党议员。1991年大选中，SDP取得历史性突破，赢得波东巴西、武吉甘柏（Bukit Gombak）和义顺中（Nee Soon Central）三个议席，得票率达48.6%，为独立以来反对党最佳成绩。\n\n然而，1993年党内爆发严重内讧。詹时中与中央执行委员会（CEC）及当时被其招揽入党的徐顺全（Chee Soon Juan）产生分歧。詹时中于1996年离党，转而加入新加坡人民党（SPP）。徐顺全此后接任秘书长，领导SDP至今。1997年大选中，SDP全军覆没，此后再未获得国会议席。\n\nSDP主张加强公民自由、扩大社会保护、增加社会福利支出、推动教育医疗住房改革，并呼吁调整移民政策。在国际层面，SDP是自由国际（Liberal International）和亚洲自由民主人士委员会（Council of Asian Liberals and Democrats）的成员。近年来，SDP持续参与选举。在2025年大选中，徐顺全在三巴旺西单选区（Sembawang West SMC）获46.81%得票率，虽未能当选但表现接近。主席保罗·谭比亚（Paul Tambyah）在武吉班让单选区（Bukit Panjang SMC）参选。2026年2月，SDP选举产生了新一届中央执行委员会（2026-2028任期），继续由徐顺全担任秘书长、谭比亚担任主席。",
  "industries": [
    "public_administration"
  ],
  "apec_stance": "SDP作为新加坡反对党，其政策主张聚焦国内社会改革，对APEC事务的直接参与有限。SDP是自由国际（Liberal International）和亚洲自由民主人士委员会成员，在民主和人权议题上有国际联系。",
  "profile": {
    "source_url": "https://upload.wikimedia.org/wikipedia/en/thumb/0/0d/Logo_of_the_SDP.svg/330px-Logo_of_the_SDP.svg.png",
    "local_path": null
  },
  "collection_meta": {
    "collection_date": "2026-04-16",
    "phase": "phase2_deep_profile",
    "data_sources": [
      "wikidata",
      "wikipedia",
      "official_website"
    ],
    "completeness_score": 92,
    "notes": "Enriched with web search: related entities, APEC stance (score: 92)"
  }
}