{
  "person_id": "SG-PERSON-000201",
  "wikidata_qid": "Q96490593",
  "name": "陈杰豪 / Tan Kiat How",
  "name_zh": "陈杰豪",
  "name_en": "Tan Kiat How",
  "aliases": [
    "Tan Kiat How",
    "陈杰豪"
  ],
  "nationality": "SG",
  "gender": "male",
  "birth_date": "1977",
  "birth_place": "Singapore",
  "contacts": [],
  "current_positions": [
    "新加坡卫生部高级政务部长",
    "新加坡数码发展及新闻部高级政务部长",
    "新加坡东海岸集选区国会议员（甘榜菜市分区）",
    "人民行动党党员"
  ],
  "education": [
    {
      "institution": "University of Illinois at Urbana-Champaign",
      "degree": "Bachelor of Arts",
      "field": "Economics"
    },
    {
      "institution": "University of Illinois at Urbana-Champaign",
      "degree": "Bachelor of Engineering",
      "field": "Computer Engineering"
    },
    {
      "institution": "Stanford University",
      "degree": "Master",
      "field": "Management"
    },
    {
      "institution": "Harvard University John F. Kennedy School of Government",
      "degree": null,
      "field": "Mason Fellow"
    }
  ],
  "work_experience": [
    {
      "organization": "新加坡教育部",
      "position": "IT顾问（国家电脑局奖学金）"
    },
    {
      "organization": "新加坡通讯及新闻部（MCI）",
      "position": "副秘书（网络与科技）"
    },
    {
      "organization": "资讯通信媒体发展局（IMDA）",
      "position": "首席执行官（2017年1月-2020年6月）"
    },
    {
      "organization": "个人数据保护委员会（PDPC）",
      "position": "专员"
    },
    {
      "organization": "新加坡总理公署",
      "position": "政务部长（2020-2021）"
    },
    {
      "organization": "新加坡国家发展部",
      "position": "政务部长（2020-2022），高级政务部长（2022-2025）"
    },
    {
      "organization": "新加坡通讯及新闻部",
      "position": "政务部长（2021-2022），高级政务部长（2022）"
    },
    {
      "organization": "新加坡卫生部",
      "position": "高级政务部长（2025至今）"
    },
    {
      "organization": "新加坡数码发展及新闻部",
      "position": "高级政务部长（2022至今）"
    },
    {
      "organization": "REACH（政府反馈机构）",
      "position": "主席"
    }
  ],
  "person_relationships": [],
  "social_accounts": [],
  "family_members": [
    {
      "relationship": "spouse",
      "name": "妻子（姓名未公开）"
    },
    {
      "relationship": "child",
      "name": "长子Isaac（2020年8月5日出生）"
    },
    {
      "relationship": "child",
      "name": "第二名子女"
    }
  ],
  "political_stances": [
    {
      "date": null,
      "topic": null,
      "stance_content": "人民行动党（PAP）成员",
      "source": null
    },
    {
      "date": null,
      "topic": null,
      "stance_content": "关注数码发展和智慧国建设",
      "source": null
    },
    {
      "date": null,
      "topic": null,
      "stance_content": "推动5G网络部署和全国光纤到户基础设施建设",
      "source": null
    }
  ],
  "major_achievements": [
    {
      "date": null,
      "organization": null,
      "achievement": "参与制定「智慧国2015」蓝图"
    },
    {
      "date": null,
      "organization": null,
      "achievement": "推动全国光纤到户基础设施建设"
    },
    {
      "date": null,
      "organization": null,
      "achievement": "在IMDA任内推动5G频谱分配"
    },
    {
      "date": null,
      "organization": null,
      "achievement": "2020年建立SG Digital Office"
    },
    {
      "date": null,
      "organization": null,
      "achievement": "2025年大选中以58.73%得票率连任东海岸集选区"
    }
  ],
  "biography_summary": "陈杰豪（Tan Kiat How，1977年生），新加坡政治人物和前高级公务员。华中初级学院毕业后，获伊利诺伊大学计算机工程和经济学双学士学位，后在斯坦福大学取得管理学硕士学位，并获哈佛大学肯尼迪学院梅森学者资格。曾在公共服务领域服务近20年，以电脑工程师身份开始职业生涯，参与制定「智慧国2015」蓝图，推动全国光纤到户基础设施建设。曾任资讯通信媒体发展局（IMDA）首席执行官兼个人数据保护委员会专员。2020年以人民行动党候选人身份首次参选东海岸集选区并当选国会议员，先后担任总理公署、国家发展部、通讯及新闻部政务部长及高级政务部长。2025年大选中连任后，调任卫生部高级政务部长，同时兼任数码发展及新闻部高级政务部长。已婚，育有两名子女。",
  "profile": null,
  "collection_meta": {
    "collection_date": "2026-04-17",
    "phase": "phase4_person_profile",
    "data_sources": [
      "https://en.wikipedia.org/wiki/Tan_Kiat_How",
      "https://www.pap.org.sg/representative/tan-kiat-how/",
      "https://www.parliament.gov.sg/mps/list-of-current-mps/mp/details/tan-kiat-how",
      "https://wiki.sg/p/Tan_Kiat_How_(Singapore_Politician)"
    ],
    "completeness_score": 80,
    "notes": "Collected via web search. Wikipedia has comprehensive biography."
  }
}